gutec/__init__.py
gutec/cli.py
gutec/gparser.py
gutec/grammar.py
gutec/gutec.py
gutec/lexer.py
gutec/scope.py
gutec/semantic_analysis.py
gutec/tokens.py
gutec/utilities.py
gutec-0.3.1.dist-info/LICENSE
gutec-0.3.1.dist-info/METADATA
gutec-0.3.1.dist-info/WHEEL
gutec-0.3.1.dist-info/entry_points.txt
gutec-0.3.1.dist-info/top_level.txt
gutec-0.3.1.dist-info/RECORD
