Metadata-Version: 2.1
Name: gutec
Version: 0.3.1
Summary: An Alan++ complient compiler
Home-page: UNKNOWN
Author: Michael Gutierrez
Author-email: mike97.gutierrez@gmail.com
License: UNKNOWN
Platform: UNKNOWN
Classifier: Programming Language :: Python :: 3
Classifier: License :: OSI Approved :: MIT License
Classifier: Operating System :: OS Independent
Requires-Dist: Click
Requires-Dist: treelib
Requires-Dist: BeautifulTable
